hdcorepy/Client.py
hdcorepy/__init__.py
hdcorepy-0.0.2.dist-info/LICENSE.txt
hdcorepy-0.0.2.dist-info/METADATA
hdcorepy-0.0.2.dist-info/WHEEL
hdcorepy-0.0.2.dist-info/top_level.txt
hdcorepy-0.0.2.dist-info/RECORD
