Metadata-Version: 2.1
Name: hdcorepy
Version: 0.0.2
Summary: A simple framework for using the HostDime API in Python
Home-page: https://github.com/jpadmin/Hdcore
Author: John Paul K J
Author-email: polestar2john@gmail.com
License: UNKNOWN
Platform: UNKNOWN
Classifier: Programming Language :: Python :: 2
Classifier: License :: OSI Approved :: MIT License
Classifier: Operating System :: OS Independent
